[{"graph": {"id": "asdiv-1091", "metadata": {"text span": "There is a snail problem in Centerville."}, "nodes": {}, "edges": []}}, {"graph": {"id": "asdiv-1091", "metadata": {"text span": "People work together to get rid 3,482 snails, but 8,278 of them remain."}, "nodes": {"1": {"label": "Centerville", "metadata": {"entity": "snail", "quantity": "3482", "unit": "", "attribute": "get rid", "reference": ""}}, "2": {"label": "Centerville", "metadata": {"entity": "snail", "quantity": "8278", "unit": "", "attribute": "remain", "reference": ""}}}, "edges": []}}, {"graph": {"id": "asdiv-1091", "metadata": {"text span": "About how many snails were originally in Centerville?", "comments": "", "flagged": "", "background knowledge": "", "low confidence": ""}, "nodes": {"1": {"label": "Centerville", "metadata": {"entity": "snail", "quantity": "3482", "unit": "", "attribute": "get rid", "reference": ""}}, "2": {"label": "Centerville", "metadata": {"entity": "snail", "quantity": "8278", "unit": "", "attribute": "remain", "reference": ""}}, "3": {"label": "Centerville", "metadata": {"entity": "snail", "quantity": "x1", "unit": "", "attribute": "originally", "reference": ""}}, "CQ": {"label": "Centerville", "metadata": {"entity": "snail", "quantity": "11760", "unit": "", "attribute": "originally", "reference": "x1"}}}, "edges": [{"id": "4", "source": "1", "target": "3", "relation": "part-whole", "metadata": {}}, {"id": "5", "source": "2", "target": "3", "relation": "part-whole", "metadata": {}}]}}]