[{"graph": {"id": "asdiv-0066", "metadata": {"text span": "There were 105 parents in the program and 698 pupils, too."}, "nodes": {"1": {"label": "Program", "metadata": {"entity": "parents", "quantity": "105", "unit": "", "attribute": "", "reference": ""}}, "2": {"label": "Program", "metadata": {"entity": "pupil", "quantity": "698", "unit": "", "attribute": "", "reference": ""}}}, "edges": []}}, {"graph": {"id": "asdiv-0066", "metadata": {"text span": "How many people were present in the program?", "comments": "", "flagged": "False", "background knowledge": "True", "low confidence": "False"}, "nodes": {"1": {"label": "Program", "metadata": {"entity": "parents", "quantity": "105", "unit": "", "attribute": "", "reference": ""}}, "2": {"label": "Program", "metadata": {"entity": "pupil", "quantity": "698", "unit": "", "attribute": "", "reference": ""}}, "3": {"label": "Program", "metadata": {"entity": "people", "quantity": "x1", "unit": "", "attribute": "", "reference": ""}}, "CQ": {"label": "Program", "metadata": {"entity": "people", "quantity": "803", "unit": "", "attribute": "", "reference": "x1"}}}, "edges": [{"id": "4", "source": "1", "target": "3", "relation": "part-whole", "metadata": {}}, {"id": "5", "source": "2", "target": "3", "relation": "part-whole", "metadata": {}}]}}]