[{"graph": {"id": "asdiv-0368", "metadata": {"text span": "Next on her list are the homeless people where she spent a total of $900.00."}, "nodes": {"1": {"label": "She", "metadata": {"entity": "money", "quantity": "900.00", "unit": "$", "attribute": "homeless people", "reference": ""}}}, "edges": []}}, {"graph": {"id": "asdiv-0368", "metadata": {"text span": "If she gave $325.00 to the first set of homeless families and $260.00 to the second set of families,"}, "nodes": {"1": {"label": "She", "metadata": {"entity": "money", "quantity": "900.00", "unit": "$", "attribute": "homeless people", "reference": ""}}, "2": {"label": "She", "metadata": {"entity": "money", "quantity": "325.00", "unit": "$", "attribute": "first set", "reference": ""}}, "3": {"label": "She", "metadata": {"entity": "money", "quantity": "260.00", "unit": "$", "attribute": "second set", "reference": ""}}, "4": {"label": "She", "metadata": {"entity": "money", "quantity": "x1", "unit": "$", "attribute": "third set", "reference": ""}}}, "edges": [{"id": "5", "source": "2", "target": "1", "relation": "part-whole", "metadata": {}}, {"id": "6", "source": "3", "target": "1", "relation": "part-whole", "metadata": {}}, {"id": "7", "source": "4", "target": "1", "relation": "part-whole", "metadata": {}}]}}, {"graph": {"id": "asdiv-0368", "metadata": {"text span": "how much did she give to the last set of homeless families?", "comments": "", "flagged": "", "background knowledge": "", "low confidence": ""}, "nodes": {"1": {"label": "She", "metadata": {"entity": "money", "quantity": "900.00", "unit": "$", "attribute": "homeless people", "reference": ""}}, "2": {"label": "She", "metadata": {"entity": "money", "quantity": "325.00", "unit": "$", "attribute": "first set", "reference": ""}}, "3": {"label": "She", "metadata": {"entity": "money", "quantity": "260.00", "unit": "$", "attribute": "second set", "reference": ""}}, "4": {"label": "She", "metadata": {"entity": "money", "quantity": "x1", "unit": "$", "attribute": "last set", "reference": ""}}, "CQ": {"label": "She", "metadata": {"entity": "money", "quantity": "315", "unit": "$", "attribute": "last set", "reference": "x1"}}}, "edges": [{"id": "5", "source": "2", "target": "1", "relation": "part-whole", "metadata": {}}, {"id": "6", "source": "3", "target": "1", "relation": "part-whole", "metadata": {}}, {"id": "7", "source": "4", "target": "1", "relation": "part-whole", "metadata": {}}]}}]