[{"graph": {"id": "asdiv-0091", "metadata": {"text span": "Michael has some fish in his fish tank."}, "nodes": {}, "edges": []}}, {"graph": {"id": "asdiv-0091", "metadata": {"text span": "Ben gave him 18 more fish."}, "nodes": {"1": {"label": "Michael", "metadata": {"entity": "fish", "quantity": "x1", "unit": "", "attribute": "", "reference": ""}}, "2": {"label": "Michael", "metadata": {"entity": "fish", "quantity": "x2", "unit": "", "attribute": "", "reference": ""}}, "3": {"label": "Ben", "metadata": {"entity": "fish", "quantity": "x3", "unit": "", "attribute": "", "reference": ""}}, "4": {"label": "Ben", "metadata": {"entity": "fish", "quantity": "x4", "unit": "", "attribute": "", "reference": ""}}}, "edges": [{"id": "5", "source": "1", "target": "2", "relation": "transfer", "metadata": {"X1": "18", "X2": ["fish", "", ""], "X3": "Michael", "X4": "Ben"}}, {"id": "6", "source": "3", "target": "4", "relation": "transfer", "metadata": {"X1": "18", "X2": ["fish", "", ""], "X3": "Michael", "X4": "Ben"}}]}}, {"graph": {"id": "asdiv-0091", "metadata": {"text span": "Now he has 49."}, "nodes": {"1": {"label": "Michael", "metadata": {"entity": "fish", "quantity": "x1", "unit": "", "attribute": "", "reference": ""}}, "2": {"label": "Michael", "metadata": {"entity": "fish", "quantity": "49", "unit": "", "attribute": "", "reference": ""}}, "3": {"label": "Ben", "metadata": {"entity": "fish", "quantity": "x3", "unit": "", "attribute": "", "reference": ""}}, "4": {"label": "Ben", "metadata": {"entity": "fish", "quantity": "x4", "unit": "", "attribute": "", "reference": ""}}}, "edges": [{"id": "5", "source": "1", "target": "2", "relation": "transfer", "metadata": {"X1": "18", "X2": ["fish", "", ""], "X3": "Michael", "X4": "Ben"}}, {"id": "6", "source": "3", "target": "4", "relation": "transfer", "metadata": {"X1": "18", "X2": ["fish", "", ""], "X3": "Michael", "X4": "Ben"}}]}}, {"graph": {"id": "asdiv-0091", "metadata": {"text span": "How many fish did he have to begin with?", "comments": "", "flagged": "", "background knowledge": "", "low confidence": ""}, "nodes": {"1": {"label": "Michael", "metadata": {"entity": "fish", "quantity": "x1", "unit": "", "attribute": "", "reference": ""}}, "2": {"label": "Michael", "metadata": {"entity": "fish", "quantity": "49", "unit": "", "attribute": "", "reference": ""}}, "3": {"label": "Ben", "metadata": {"entity": "fish", "quantity": "x3", "unit": "", "attribute": "", "reference": ""}}, "4": {"label": "Ben", "metadata": {"entity": "fish", "quantity": "x4", "unit": "", "attribute": "", "reference": ""}}, "CQ": {"label": "Michael", "metadata": {"entity": "fish", "quantity": "31", "unit": "", "attribute": "", "reference": "x1"}}}, "edges": [{"id": "5", "source": "1", "target": "2", "relation": "transfer", "metadata": {"X1": "18", "X2": ["fish", "", ""], "X3": "Michael", "X4": "Ben"}}, {"id": "6", "source": "3", "target": "4", "relation": "transfer", "metadata": {"X1": "18", "X2": ["fish", "", ""], "X3": "Michael", "X4": "Ben"}}]}}]