[{"graph": {"id": "mawps-256", "metadata": {"text span": "Ned had 15 video games."}, "nodes": {"1": {"label": "Ned", "metadata": {"entity": "video game", "quantity": "15", "unit": "", "attribute": "", "reference": ""}}}, "edges": []}}, {"graph": {"id": "mawps-256", "metadata": {"text span": "6 of them weren't working."}, "nodes": {"1": {"label": "Ned", "metadata": {"entity": "video game", "quantity": "15", "unit": "", "attribute": "", "reference": ""}}, "2": {"label": "Ned", "metadata": {"entity": "video game", "quantity": "x1", "unit": "", "attribute": "", "reference": ""}}}, "edges": [{"id": "3", "source": "1", "target": "2", "relation": "transfer", "metadata": {"X1": "6", "X2": ["video game", "", ""], "X3": "", "X4": "Ned"}}]}}, {"graph": {"id": "mawps-256", "metadata": {"text span": "If he wanted to sell the working games for $7 each,"}, "nodes": {"1": {"label": "Ned", "metadata": {"entity": "video game", "quantity": "15", "unit": "", "attribute": "", "reference": ""}}, "2": {"label": "Ned", "metadata": {"entity": "video game", "quantity": "x1", "unit": "", "attribute": "", "reference": ""}}, "4": {"label": "Ned", "metadata": {"entity": "money", "quantity": "x2", "unit": "$", "attribute": "", "reference": ""}}}, "edges": [{"id": "3", "source": "1", "target": "2", "relation": "transfer", "metadata": {"X1": "6", "X2": ["video game", "", ""], "X3": "", "X4": "Ned"}}, {"id": "5", "source": "4", "target": "2", "relation": "rate", "metadata": {"X1": "7", "X2": ["money", "", "$"], "X3": ["video game", "", ""]}}]}}, {"graph": {"id": "mawps-256", "metadata": {"text span": "how much money could he earn?", "comments": "", "flagged": "", "background knowledge": "", "low confidence": ""}, "nodes": {"1": {"label": "Ned", "metadata": {"entity": "video game", "quantity": "15", "unit": "", "attribute": "", "reference": ""}}, "2": {"label": "Ned", "metadata": {"entity": "video game", "quantity": "x1", "unit": "", "attribute": "", "reference": ""}}, "4": {"label": "Ned", "metadata": {"entity": "money", "quantity": "x2", "unit": "$", "attribute": "", "reference": ""}}, "CQ": {"label": "Ned", "metadata": {"entity": "money", "quantity": "63", "unit": "$", "attribute": "", "reference": "x2"}}}, "edges": [{"id": "3", "source": "1", "target": "2", "relation": "transfer", "metadata": {"X1": "6", "X2": ["video game", "", ""], "X3": "", "X4": "Ned"}}, {"id": "5", "source": "4", "target": "2", "relation": "rate", "metadata": {"X1": "7", "X2": ["money", "", "$"], "X3": ["video game", "", ""]}}]}}]