[{"graph": {"id": "mawps-300", "metadata": {"text span": "Tim got 3 nickels and 13 dimes for shining shoes, and in his tip jar found 7 dimes and 9 half-dollars."}, "nodes": {"1": {"label": "Tim", "metadata": {"entity": "money", "quantity": "3", "unit": "nickel", "attribute": "shining shoes", "reference": ""}}, "2": {"label": "Tim", "metadata": {"entity": "money", "quantity": "13", "unit": "dime", "attribute": "shining shoes", "reference": ""}}, "3": {"label": "Tim", "metadata": {"entity": "money", "quantity": "7", "unit": "dime", "attribute": "tip jar", "reference": ""}}, "4": {"label": "Tim", "metadata": {"entity": "money", "quantity": "9", "unit": "half-dollar", "attribute": "tip jar", "reference": ""}}}, "edges": []}}, {"graph": {"id": "mawps-300", "metadata": {"text span": "How much money did Tim get?", "comments": "requires conversion of money units", "flagged": "", "background knowledge": "True", "low confidence": ""}, "nodes": {"1": {"label": "Tim", "metadata": {"entity": "money", "quantity": "3", "unit": "nickel", "attribute": "shining shoes", "reference": ""}}, "2": {"label": "Tim", "metadata": {"entity": "money", "quantity": "13", "unit": "dime", "attribute": "shining shoes", "reference": ""}}, "3": {"label": "Tim", "metadata": {"entity": "money", "quantity": "7", "unit": "dime", "attribute": "tip jar", "reference": ""}}, "4": {"label": "Tim", "metadata": {"entity": "money", "quantity": "9", "unit": "half-dollar", "attribute": "tip jar", "reference": ""}}, "5": {"label": "Tim", "metadata": {"entity": "money", "quantity": "x1", "unit": "dollar", "attribute": "", "reference": ""}}, "CQ": {"label": "Tim", "metadata": {"entity": "money", "quantity": "6.65", "unit": "dollar", "attribute": "", "reference": "x1"}}}, "edges": [{"id": "6", "source": "1", "target": "5", "relation": "explicit-times", "metadata": {"X1": "0.05", "X2": ["money", "", "nickel"], "X3": "Tim", "X4": "Tim"}}, {"id": "7", "source": "2", "target": "5", "relation": "explicit-times", "metadata": {"X1": "0.10", "X2": ["money", "", "dime"], "X3": "Tim", "X4": "Tim"}}, {"id": "8", "source": "3", "target": "5", "relation": "explicit-times", "metadata": {"X1": "0.10", "X2": ["money", "", "dime"], "X3": "Tim", "X4": "Tim"}}, {"id": "9", "source": "4", "target": "5", "relation": "explicit-times", "metadata": {"X1": "0.10", "X2": ["money", "", "half-dollar"], "X3": "Tim", "X4": "Tim"}}]}}]