[{"graph": {"id": "mawps-1368", "metadata": {"text span": "A cereal box holds 18 cups of cereal."}, "nodes": {"1": {"label": "Cereal Box", "metadata": {"entity": "Cup", "quantity": "18", "unit": "", "attribute": "", "reference": ""}}}, "edges": []}}, {"graph": {"id": "mawps-1368", "metadata": {"text span": "Each serving is 2 cups."}, "nodes": {"1": {"label": "Cereal Box", "metadata": {"entity": "Cup", "quantity": "18", "unit": "", "attribute": "", "reference": ""}}, "2": {"label": "Cereal Box", "metadata": {"entity": "Serving", "quantity": "c2", "unit": "", "attribute": "", "reference": ""}}}, "edges": [{"id": "3", "source": "1", "target": "2", "relation": "rate", "metadata": {"X1": "1/2", "X2": ["Cup", "", ""], "X3": ["Serving", "", ""]}}]}}, {"graph": {"id": "mawps-1368", "metadata": {"text span": "How many servings are in the whole box?", "comments": "", "flagged": "", "background knowledge": "", "low confidence": ""}, "nodes": {"1": {"label": "Cereal Box", "metadata": {"entity": "Cup", "quantity": "18", "unit": "", "attribute": "", "reference": ""}}, "2": {"label": "Cereal Box", "metadata": {"entity": "Serving", "quantity": "c2", "unit": "", "attribute": "", "reference": ""}}, "CQ": {"label": "Cereal Box", "metadata": {"entity": "Serving", "quantity": "9", "unit": "", "attribute": "", "reference": "c2"}}}, "edges": [{"id": "3", "source": "1", "target": "2", "relation": "rate", "metadata": {"X1": "1/2", "X2": ["Cup", "", ""], "X3": ["Serving", "", ""]}}]}}]