[{"graph": {"id": "mawps-207", "metadata": {"text span": "Keith spent $6.51 on a rabbit toy, $5.79 on pet food, and a cage cost him $12.51."}, "nodes": {"1": {"label": "Keith", "metadata": {"entity": "money", "quantity": "6.51", "unit": "$", "attribute": "rabbit toy", "reference": ""}}, "2": {"label": "Keith", "metadata": {"entity": "money", "quantity": "5.79", "unit": "$", "attribute": "pet food", "reference": ""}}, "3": {"label": "Keith", "metadata": {"entity": "money", "quantity": "12.51", "unit": "$", "attribute": "cage", "reference": ""}}, "4": {"label": "Keith", "metadata": {"entity": "money", "quantity": "x1", "unit": "$", "attribute": "spent", "reference": ""}}}, "edges": [{"id": "5", "source": "1", "target": "4", "relation": "part-whole", "metadata": {}}, {"id": "6", "source": "2", "target": "4", "relation": "part-whole", "metadata": {}}, {"id": "7", "source": "3", "target": "4", "relation": "part-whole", "metadata": {}}]}}, {"graph": {"id": "mawps-207", "metadata": {"text span": "He found a dollar bill on the ground."}, "nodes": {"1": {"label": "Keith", "metadata": {"entity": "money", "quantity": "6.51", "unit": "$", "attribute": "rabbit toy", "reference": ""}}, "2": {"label": "Keith", "metadata": {"entity": "money", "quantity": "5.79", "unit": "$", "attribute": "pet food", "reference": ""}}, "3": {"label": "Keith", "metadata": {"entity": "money", "quantity": "12.51", "unit": "$", "attribute": "cage", "reference": ""}}, "4": {"label": "Keith", "metadata": {"entity": "money", "quantity": "x1", "unit": "$", "attribute": "spent", "reference": ""}}, "8": {"label": "Keith", "metadata": {"entity": "money", "quantity": "x2", "unit": "$", "attribute": "", "reference": ""}}}, "edges": [{"id": "5", "source": "1", "target": "4", "relation": "part-whole", "metadata": {}}, {"id": "6", "source": "2", "target": "4", "relation": "part-whole", "metadata": {}}, {"id": "7", "source": "3", "target": "4", "relation": "part-whole", "metadata": {}}, {"id": "9", "source": "4", "target": "8", "relation": "transfer", "metadata": {"X1": "1.00", "X2": ["money", "", "$"], "X3": "", "X4": "Keith"}}]}}, {"graph": {"id": "mawps-207", "metadata": {"text span": "What was the total cost of Keith's purchases?", "comments": "", "flagged": "", "background knowledge": "", "low confidence": ""}, "nodes": {"1": {"label": "Keith", "metadata": {"entity": "money", "quantity": "6.51", "unit": "$", "attribute": "rabbit toy", "reference": ""}}, "2": {"label": "Keith", "metadata": {"entity": "money", "quantity": "5.79", "unit": "$", "attribute": "pet food", "reference": ""}}, "3": {"label": "Keith", "metadata": {"entity": "money", "quantity": "12.51", "unit": "$", "attribute": "cage", "reference": ""}}, "4": {"label": "Keith", "metadata": {"entity": "money", "quantity": "x1", "unit": "$", "attribute": "spent", "reference": ""}}, "8": {"label": "Keith", "metadata": {"entity": "money", "quantity": "x2", "unit": "$", "attribute": "", "reference": ""}}, "CQ": {"label": "Keith", "metadata": {"entity": "money", "quantity": "24.81", "unit": "$", "attribute": "", "reference": "x1"}}}, "edges": [{"id": "5", "source": "1", "target": "4", "relation": "part-whole", "metadata": {}}, {"id": "6", "source": "2", "target": "4", "relation": "part-whole", "metadata": {}}, {"id": "7", "source": "3", "target": "4", "relation": "part-whole", "metadata": {}}, {"id": "9", "source": "4", "target": "8", "relation": "transfer", "metadata": {"X1": "1.00", "X2": ["money", "", "$"], "X3": "", "X4": "Keith"}}]}}]